Workbook

Sheet Cover
A2: WAAREE ENERGIES LIMITED — INTEGRATED 3-STATEMENT MODEL & DCF VALUATION
A4: NSE: WAAREEENER | BSE: 544277 | ISIN: INE377N01017
A6: Part III of an institutional equity research package. Historicals (FY20-FY26) sourced from company filings via Screener.in (see Part I). Forecast (FY27E-FY31E) driven entirely by editable assumptions on the Assumptions tab.
A9: How this model is built
A10: Color legend:
A11: Blue text | B11: Hardcoded input / historical actual — editable
A12: Black text | B12: Formula — do not overwrite
A13: Green text | B13: Link to another sheet
A14: Yellow fill | B14: Key assumption cells to flex for scenario analysis
A16: Tab | B16: Contents
A17: Assumptions | B17: All forecast drivers (growth, margins, capex, WC, WACC inputs) — edit here to run scenarios
A18: Income Statement | B18: FY20-FY26 actuals + FY27E-FY31E forecast P&L
A19: Balance Sheet | B19: FY20-FY26 actuals + FY27E-FY31E forecast BS, with a balance check
A20: Cash Flow | B20: FY20-FY26 actuals + FY27E-FY31E forecast CFO/CFI/CFF and FCFF
A21: Schedules | B21: Capex/Depreciation roll-forward and Debt roll-forward supporting the 3 statements
A22: Ratios | B22: Profitability, leverage, efficiency ratios recomputed from the model for all 12 years
A23: DCF Valuation | B23: WACC build, FCFF discounting, terminal value, intrinsic value per share
... A25: Checks | B25: Balance sheet integrity and other error checks — must show zero/TRUE before use

Sheet Assumptions
A1: ASSUMPTIONS — Forecast Drivers (edit blue cells to run scenarios)
A3: Forecast Driver | B3: FY27E | C3: FY28E | D3: FY29E | E3: FY30E | F3: FY31E
A4: Revenue growth % YoY | B4: 0.35 | C4: 0.25 | D4: 0.2 | E4: 0.15 | F4: 0.12
A5: EBITDA margin % | B5: 0.2 | C5: 0.205 | D5: 0.21 | E5: 0.215 | F5: 0.22
A6: D&A (% of revenue) | B6: 0.045 | C6: 0.045 | D6: 0.043 | E6: 0.04 | F6: 0.038
A7: Capex (% of revenue) | B7: 0.08 | C7: 0.07 | D7: 0.06 | E7: 0.05 | F7: 0.045
A8: Increase in Net Working Capital (% of Δ Revenue) | B8: 0.15 | C8: 0.14 | D8: 0.12 | E8: 0.1 | F8: 0.1
A9: Source/rationale for the five rows above: Part II Section 2.2 (growth fades from FY27's capacity-ramp-driven 35% toward a 12% terminal-adjacent rate; margin expands as cell backward-integration reduces ALMM List-II cost pass-through; capex intensity tapers as the FY26 acquisition/cell-capex cycle normalizes; NWC intensity stays elevated vs. FY25's 35-day cycle, only partially normalizing from FY26's 90-day stress level).
A11: Single-value assumptions
A12: Tax rate (effective) | B12: 0.25
A13: Dividend payout ratio (% of net profit) | B13: 0.02
A14: Debt-financed capex (%) | B14: 0.2
A15: Other Liabilities as % of Revenue (forecast) | B15: ='Balance Sheet'!H9/'Income Statement'!H5 -> 0.46972152
A17: WACC Build-Up
A18: Risk-free rate (India 10Y G-Sec, Jul-2026) | B18: 0.067
A19: Equity beta (levered) | B19: 1.05
A20: Equity Risk Premium — India | B20: 0.07
A21: Cost of Equity (Ke = Rf + β × ERP) | B21: =B18+B19*B20 -> 0.1405
A22: Pre-tax cost of debt (Kd) | B22: 0.085
A23: Post-tax cost of debt | B23: =B22*(1-B12) -> 0.06375
A24: Market Capitalization (₹ Cr) | B24: 83000
A25: Total Debt (₹ Cr, latest) | B25: ='Balance Sheet'!H8 -> 3213
A26: Weight of Equity (E/V, market value) | B26: =B24/(B24+B25) -> 0.96273184
A27: Weight of Debt (D/V, market value) | B27: =B25/(B24+B25) -> 0.037268161
A28: WACC | B28: =B26*B21+B27*B23 -> 0.13763967
A29: Terminal growth rate (g) | B29: 0.05
A31: DCF Supporting Inputs
A32: Cash & Investments proxy (₹ Cr) | B32: 953
A33: Net Debt (₹ Cr) | B33: =B25-B32 -> 2260
A34: Diluted shares outstanding (Cr) | B34: 30.1
A35: Current Market Price, CMP (₹/share) | B35: 2886

Sheet Income Statement
A1: INCOME STATEMENT — FY20-FY26 Actual, FY27E-FY31E Forecast
A3: ₹ Crore, Consolidated | B3: FY20 | C3: FY21 | D3: FY22 | E3: FY23 | F3: FY24 | G3: FY25 | H3: FY26 | I3: FY27E | J3: FY28E | K3: FY29E | L3: FY30E | M3: FY31E
A5: Revenue | B5: 1996 | C5: 1953 | D5: 2854 | E5: 6751 | F5: 11398 | G5: 14444 | H5: 26537 | I5: =H5*(1+Assumptions!B4) -> 35824.95 | J5: =I5*(1+Assumptions!C4) -> 44781.188 | K5: =J5*(1+Assumptions!D4) -> 53737.425 | L5: =K5*(1+Assumptions!E4) -> 61798.039 | M5: =L5*(1+Assumptions!F4) -> 69213.803
A6: Revenue growth % YoY | C6: =C5/B5-1 -> -0.021543086 | D6: =D5/C5-1 -> 0.46134153 | E6: =E5/D5-1 -> 1.365452 | F6: =F5/E5-1 -> 0.68834247 | G6: =G5/F5-1 -> 0.26723987 | H6: =H5/G5-1 -> 0.83723345 | I6: =I5/H5-1 -> 0.35 | J6: =J5/I5-1 -> 0.25 | ... M6: =M5/L5-1 -> 0.12
A7: EBITDA (Operating Profit) | B7: 93 | C7: 85 | D7: 106 | E7: 836 | F7: 1574 | G7: 2722 | H7: 5909 | I7: =I5*Assumptions!B5 -> 7164.99 | J7: =J5*Assumptions!C5 -> 9180.1434 | K7: =K5*Assumptions!D5 -> 11284.859 | L7: =L5*Assumptions!E5 -> 13286.578 | M7: =M5*Assumptions!F5 -> 15227.037
A8: EBITDA margin % | B8: =B7/B5 -> 0.046593186 | C8: =C7/C5 -> 0.043522785 | D8: =D7/D5 -> 0.037140855 | E8: =E7/E5 -> 0.12383351 | F8: =F7/F5 -> 0.1380944 | G8: =G7/G5 -> 0.18845195 | H8: =H7/H5 -> 0.22267023 | I8: =I7/I5 -> 0.2 | ... M8: =M7/M5 -> 0.22
A9: Less: Depreciation & Amortization | B9: 27 | C9: 29 | D9: 43 | E9: 164 | F9: 277 | G9: 402 | H9: 990 | I9: =Schedules!I7 -> 1612.1227 | J9: =Schedules!J7 -> 2015.1534 | K9: =Schedules!K7 -> 2310.7093 | L9: =Schedules!L7 -> 2471.9216 | M9: =Schedules!M7 -> 2630.1245
A10: EBIT | B10: =B7-B9 -> 66 | C10: =C7-C9 -> 56 | D10: =D7-D9 -> 63 | E10: =E7-E9 -> 672 | F10: =F7-F9 -> 1297 | G10: =G7-G9 -> 2320 | H10: =H7-H9 -> 4919 | I10: =I7-I9 -> 5552.8673 | ... M10: =M7-M9 -> 12596.912
A11: Add: Other Income | B11: 25 | C11: 45 | D11: 97 | E11: 88 | F11: 576 | G11: 398 | H11: 413 | I11: =0 -> 0 | J11: =0 -> 0 | K11: =0 -> 0 | L11: =0 -> 0 | M11: =0 -> 0
A12: Less: Interest Expense | B12: 34 | C12: 31 | D12: 41 | E12: 82 | F12: 140 | G12: 152 | H12: 280 | I12: =Schedules!I17 -> 297.46597 | J12: =Schedules!J17 -> 348.47174 | K12: =Schedules!K17 -> 402.52263 | L12: =Schedules!L17 -> 456.19289 | M12: =Schedules!M17 -> 508.93133
A13: Profit Before Tax (PBT) | B13: =B10+B11-B12 -> 57 | C13: =C10+C11-C12 -> 70 | D13: =D10+D11-D12 -> 119 | E13: =E10+E11-E12 -> 678 | F13: =F10+F11-F12 -> 1733 | G13: =G10+G11-G12 -> 2566 | H13: =H10+H11-H12 -> 5052 | I13: =I10+I11-I12 -> 5255.4013 | ... M13: =M10+M11-M12 -> 12087.981
A14: Effective tax rate % | B14: 0.31 | C14: 0.31 | D14: 0.33 | E14: 0.26 | F14: 0.27 | G14: 0.25 | H14: 0.23 | I14: =Assumptions!$B$12 -> 0.25 | J14: =Assumptions!$B$12 -> 0.25 | K14: =Assumptions!$B$12 -> 0.25 | L14: =Assumptions!$B$12 -> 0.25 | M14: =Assumptions!$B$12 -> 0.25
A15: Less: Tax | B15: =B13*B14 -> 17.67 | C15: =C13*C14 -> 21.7 | D15: =D13*D14 -> 39.27 | E15: =E13*E14 -> 176.28 | F15: =F13*F14 -> 467.91 | G15: =G13*G14 -> 641.5 | H15: =H13*H14 -> 1161.96 | I15: =I13*I14 -> 1313.8503 | ... M15: =M13*M14 -> 3021.9952
A16: Net Profit (PAT) | B16: =B13-B15 -> 39.33 | C16: =C13-C15 -> 48.3 | D16: =D13-D15 -> 79.73 | E16: =E13-E15 -> 501.72 | F16: =F13-F15 -> 1265.09 | G16: =G13-G15 -> 1924.5 | H16: =H13-H15 -> 3890.04 | I16: =I13-I15 -> 3941.551 | ... M16: =M13-M15 -> 9065.9857
A17: Net Profit Margin % | B17: =B16/B5 -> 0.019704409 | C17: =C16/C5 -> 0.024731183 | D17: =D16/D5 -> 0.02793623 | E17: =E16/E5 -> 0.074317879 | F17: =F16/F5 -> 0.11099228 | G17: =G16/G5 -> 0.13323872 | H17: =H16/H5 -> 0.14658929 | I17: =I16/I5 -> 0.11002251 | ... M17: =M16/M5 -> 0.13098523
A18: EPS (₹) | B18: 2.12 | C18: 2.5 | D18: 3.84 | E18: 24.49 | F18: 62.76 | G18: 65 | H18: 129.02 | I18: =I16/Assumptions!$B$34 -> 130.94854 | J18: =J16/Assumptions!$B$34 -> 169.8468 | K18: =K16/Assumptions!$B$34 -> 213.57875 | L18: =L16/Assumptions!$B$34 -> 258.10126 | M18: =M16/Assumptions!$B$34 -> 301.19554
A20: Note: forecast (blue-free, black formula) cells recalculate automatically from the Assumptions tab. Historical (blue) cells are hardcoded actuals from Part I / Screener.in and should not be overwritten.

Sheet Schedules
A1: SUPPORTING SCHEDULES — Capex/Depreciation and Debt Roll-Forward (Forecast Only)
A3: ₹ Crore | I3: FY27E | J3: FY28E | K3: FY29E | L3: FY30E | M3: FY31E
A4: Capex & Depreciation Roll-Forward
A5: Opening Net Fixed Assets | I5: ='Balance Sheet'!H13 -> 7329 | J5: ='Balance Sheet'!I13 -> 8582.8733 | K5: ='Balance Sheet'!J13 -> 9702.4029 | L5: ='Balance Sheet'!K13 -> 10615.939 | M5: ='Balance Sheet'!L13 -> 11233.92
A6: Add: Capex | I6: ='Income Statement'!I5*Assumptions!B7 -> 2865.996 | J6: ='Income Statement'!J5*Assumptions!C7 -> 3134.6831 | K6: ='Income Statement'!K5*Assumptions!D7 -> 3224.2455 | L6: ='Income Statement'!L5*Assumptions!E7 -> 3089.9019 | M6: ='Income Statement'!M5*Assumptions!F7 -> 3114.6212
A7: Less: Depreciation | I7: ='Income Statement'!I5*Assumptions!B6 -> 1612.1227 | J7: ='Income Statement'!J5*Assumptions!C6 -> 2015.1534 | K7: ='Income Statement'!K5*Assumptions!D6 -> 2310.7093 | L7: ='Income Statement'!L5*Assumptions!E6 -> 2471.9216 | M7: ='Income Statement'!M5*Assumptions!F6 -> 2630.1245
A8: Closing Net Fixed Assets | I8: =I5+I6-I7 -> 8582.8733 | J8: =J5+J6-J7 -> 9702.4029 | K8: =K5+K6-K7 -> 10615.939 | L8: =L5+L6-L7 -> 11233.92 | M8: =M5+M6-M7 -> 11718.416
A10: Debt Roll-Forward
A11: Opening Debt | I11: ='Balance Sheet'!H8 -> 3213 | J11: ='Balance Sheet'!I8 -> 3786.1992 | K11: ='Balance Sheet'!J8 -> 4413.1358 | L11: ='Balance Sheet'!K8 -> 5057.9849 | M11: ='Balance Sheet'!L8 -> 5675.9653
A12: Add: Drawdowns (debt-financed capex) | I12: =I6*Assumptions!$B$14 -> 573.1992 | J12: =J6*Assumptions!$B$14 -> 626.93663 | K12: =K6*Assumptions!$B$14 -> 644.8491 | L12: =L6*Assumptions!$B$14 -> 617.98039 | M12: =M6*Assumptions!$B$14 -> 622.92423
A13: Less: Repayments | I13: =0 -> 0 | J13: =0 -> 0 | K13: =0 -> 0 | L13: =0 -> 0 | M13: =0 -> 0
A14: Closing Debt | I14: =I11+I12-I13 -> 3786.1992 | J14: =J11+J12-J13 -> 4413.1358 | K14: =K11+K12-K13 -> 5057.9849 | L14: =L11+L12-L13 -> 5675.9653 | M14: =M11+M12-M13 -> 6298.8895
A16: Average Debt (for interest calc) | I16: =(I11+I14)/2 -> 3499.5996 | J16: =(J11+J14)/2 -> 4099.6675 | K16: =(K11+K14)/2 -> 4735.5604 | L16: =(L11+L14)/2 -> 5366.9751 | M16: =(M11+M14)/2 -> 5987.4274
A17: Interest Expense | I17: =I16*Assumptions!$B$22 -> 297.46597 | J17: =J16*Assumptions!$B$22 -> 348.47174 | K17: =K16*Assumptions!$B$22 -> 402.52263 | L17: =L16*Assumptions!$B$22 -> 456.19289 | M17: =M16*Assumptions!$B$22 -> 508.93133
A19: Depreciation and Capex are modeled as % of revenue (Assumptions rows 6-7) rather than an asset-class-level schedule, consistent with Part II's methodology. Debt drawdowns assume a fixed % of capex is debt-funded (Assumptions row 14); repayments are assumed nil over the explicit forecast window — a simplification flagged for refinement against Waaree's actual debt maturity profile.

Sheet Balance Sheet
A1: BALANCE SHEET — FY20-FY26 Actual, FY27E-FY31E Forecast
A3: ₹ Crore, Consolidated | B3: FY20 | C3: FY21 | D3: FY22 | E3: FY23 | F3: FY24 | G3: FY25 | H3: FY26 | I3: FY27E | J3: FY28E | K3: FY29E | L3: FY30E | M3: FY31E
A4: Liabilities
A5: Equity Share Capital | B5: 197 | C5: 197 | D5: 197 | E5: 243 | F5: 263 | G5: 287 | H5: 288 | I5: =H5 -> 288 | J5: =I5 -> 288 | K5: =J5 -> 288 | L5: =K5 -> 288 | M5: =L5 -> 288
A6: Reserves & Surplus | B6: 101 | C6: 148 | D6: 231 | E6: 1595 | F6: 3825 | G6: 9192 | H6: 14150 | I6: =H6+'Income Statement'!I16*(1-Assumptions!$B$13) -> 18012.72 | J6: =I6+'Income Statement'!J16*(1-Assumptions!$B$13) -> 23022.861 | K6: =J6+'Income Statement'!K16*(1-Assumptions!$B$13) -> 29323.007 | L6: =K6+'Income Statement'!L16*(1-Assumptions!$B$13) -> 36936.478 | M6: =L6+'Income Statement'!M16*(1-Assumptions!$B$13) -> 45821.144
A7: Total Equity | B7: =B5+B6 -> 298 | C7: =C5+C6 -> 345 | D7: =D5+D6 -> 428 | E7: =E5+E6 -> 1838 | F7: =F5+F6 -> 4088 | G7: =G5+G6 -> 9479 | H7: =H5+H6 -> 14438 | I7: =I5+I6 -> 18300.72 | ... M7: =M5+M6 -> 46109.144
A8: Total Borrowings | B8: 157 | C8: 340 | D8: 363 | E8: 320 | F8: 553 | G8: 1199 | H8: 3213 | I8: =Schedules!I14 -> 3786.1992 | J8: =Schedules!J14 -> 4413.1358 | K8: =Schedules!K14 -> 5057.9849 | L8: =Schedules!L14 -> 5675.9653 | M8: =Schedules!M14 -> 6298.8895
A9: Other Liabilities | B9: 483 | C9: 596 | D9: 1362 | E9: 5247 | F9: 6635 | G9: 9028 | H9: 12465 | I9: ='Income Statement'!I5*Assumptions!$B$15 -> 16827.75 | J9: ='Income Statement'!J5*Assumptions!$B$15 -> 21034.688 | K9: ='Income Statement'!K5*Assumptions!$B$15 -> 25241.625 | L9: ='Income Statement'!L5*Assumptions!$B$15 -> 29027.869 | M9: ='Income Statement'!M5*Assumptions!$B$15 -> 32511.213
A10: Total Liabilities | B10: =B7+B8+B9 -> 938 | C10: =C7+C8+C9 -> 1281 | D10: =D7+D8+D9 -> 2153 | E10: =E7+E8+E9 -> 7405 | F10: =F7+F8+F9 -> 11276 | G10: =G7+G8+G9 -> 19706 | H10: =H7+H8+H9 -> 30116 | I10: =I7+I8+I9 -> 38914.669 | ... M10: =M7+M8+M9 -> 84919.246
A12: Assets
A13: Net Fixed Assets | B13: 152 | C13: 285 | D13: 625 | E13: 1105 | F13: 1450 | G13: 4051 | H13: 7329 | I13: =Schedules!I8 -> 8582.8733 | J13: =Schedules!J8 -> 9702.4029 | K13: =Schedules!K8 -> 10615.939 | L13: =Schedules!L8 -> 11233.92 | M13: =Schedules!M8 -> 11718.416
A14: Capital Work-in-Progress | B14: 40 | C14: 3 | D14: 124 | E14: 537 | F14: 1341 | G14: 1884 | H14: 3476 | I14: =$H$14 -> 3476 | J14: =$H$14 -> 3476 | K14: =$H$14 -> 3476 | L14: =$H$14 -> 3476 | M14: =$H$14 -> 3476
A15: Investments | B15: 85 | C15: 115 | D15: 143 | E15: 31 | F15: 71 | G15: 65 | H15: 953 | I15: =$H$15 -> 953 | J15: =$H$15 -> 953 | K15: =$H$15 -> 953 | L15: =$H$15 -> 953 | M15: =$H$15 -> 953
A16: Other Assets (working-capital plug) | B16: 661 | C16: 878 | D16: 1262 | E16: 5732 | F16: 8414 | G16: 13706 | H16: 18358 | I16: =I10-I13-I14-I15 -> 25902.796 | J16: =J10-J13-J14-J15 -> 34627.281 | K16: =K10-K13-K14-K15 -> 44865.678 | L16: =L10-L13-L14-L15 -> 56265.392 | M16: =M10-M13-M14-M15 -> 68771.83
A17: Forecast 'Other Assets' is solved as the balancing plug (Total Liabilities less Fixed Assets, CWIP, and Investments) rather than built bottom-up from a receivables/inventory/payables schedule — standard simplification when a full working-capital days schedule isn't separately modeled. See Checks tab for the balance verification this produces, and Part II Section 5 for the flagged refinement.
A18: Total Assets | B18: =B13+B14+B15+B16 -> 938 | C18: =C13+C14+C15+C16 -> 1281 | D18: =D13+D14+D15+D16 -> 2154 | E18: =E13+E14+E15+E16 -> 7405 | F18: =F13+F14+F15+F16 -> 11276 | G18: =G13+G14+G15+G16 -> 19706 | H18: =H13+H14+H15+H16 -> 30116 | I18: =I13+I14+I15+I16 -> 38914.669 | ... M18: =M13+M14+M15+M16 -> 84919.246
A20: Balance Check (Total Assets − Total Liabilities) | B20: =B18-B10 -> 0 | C20: =C18-C10 -> 0 | D20: =D18-D10 -> 1 | E20: =E18-E10 -> 0 | F20: =F18-F10 -> 0 | G20: =G18-G10 -> 0 | H20: =H18-H10 -> 0 | I20: =I18-I10 -> 0 | ... M20: =M18-M10 -> 0

Sheet Cash Flow
A1: CASH FLOW STATEMENT — FY20-FY26 Actual, FY27E-FY31E Forecast
A3: ₹ Crore, Consolidated | B3: FY20 | C3: FY21 | D3: FY22 | E3: FY23 | F3: FY24 | G3: FY25 | H3: FY26 | I3: FY27E | J3: FY28E | K3: FY29E | L3: FY30E | M3: FY31E
A5: Δ Net Working Capital (forecast only) | B5: n/a | C5: n/a | D5: n/a | E5: n/a | F5: n/a | G5: n/a | H5: n/a | I5: =('Income Statement'!I5-'Income Statement'!H5)*Assumptions!B8 -> 1393.1925 | J5: =('Income Statement'!J5-'Income Statement'!I5)*Assumptions!C8 -> 1253.8733 | K5: =('Income Statement'!K5-'Income Statement'!J5)*Assumptions!D8 -> 1074.7485 | L5: =('Income Statement'!L5-'Income Statement'!K5)*Assumptions!E8 -> 806.06137 | M5: =('Income Statement'!M5-'Income Statement'!L5)*Assumptions!F8 -> 741.57647
A7: Cash from Operating Activities (CFO) | B7: 83 | C7: 67 | D7: 698 | E7: 1560 | F7: 2305 | G7: 3158 | H7: 1627 | I7: ='Income Statement'!I16+'Income Statement'!I9-I5 -> 4160.4812 | J7: ='Income Statement'!J16+'Income Statement'!J9-J5 -> 5873.6689 | K7: ='Income Statement'!K16+'Income Statement'!K9-K5 -> 7664.6813 | L7: ='Income Statement'!L16+'Income Statement'!L9-L5 -> 9434.7081 | M7: ='Income Statement'!M16+'Income Statement'!M9-M5 -> 10954.534
A8: Cash from Investing Activities (CFI) | B8: -22 | C8: -250 | D8: -673 | E8: -2088 | F8: -3346 | G8: -6806 | H8: -3953 | I8: =-Schedules!I6 -> -2865.996 | J8: =-Schedules!J6 -> -3134.6831 | K8: =-Schedules!K6 -> -3224.2455 | L8: =-Schedules!L6 -> -3089.9019 | M8: =-Schedules!M6 -> -3114.6212
A9: Cash from Financing Activities (CFF) | B9: -50 | C9: 161 | D9: 101 | E9: 642 | F9: 909 | G9: 4036 | H9: 2573 | I9: =Schedules!I12-Schedules!I13-('Income Statement'!I16*Assumptions!$B$13) -> 494.36818 | J9: =Schedules!J12-Schedules!J13-('Income Statement'!J16*Assumptions!$B$13) -> 524.68885 | K9: =Schedules!K12-Schedules!K13-('Income Statement'!K16*Assumptions!$B$13) -> 516.27469 | L9: =Schedules!L12-Schedules!L13-('Income Statement'!L16*Assumptions!$B$13) -> 462.60343 | M9: =Schedules!M12-Schedules!M13-('Income Statement'!M16*Assumptions!$B$13) -> 441.60452
A10: Net Change in Cash | B10: =B7+B8+B9 -> 11 | C10: =C7+C8+C9 -> -22 | D10: =D7+D8+D9 -> 126 | E10: =E7+E8+E9 -> 114 | F10: =F7+F8+F9 -> -132 | G10: =G7+G8+G9 -> 388 | H10: =H7+H8+H9 -> 247 | I10: =I7+I8+I9 -> 1788.8534 | ... M10: =M7+M8+M9 -> 8281.5171
A12: Free Cash Flow (CFO − Capex) | B12: 32 | C12: -35 | D12: 202 | E12: 698 | F12: 968 | G12: -114 | H12: -3209 | I12: =I7-Schedules!I6 -> 1294.4852 | J12: =J7-Schedules!J6 -> 2738.9858 | K12: =K7-Schedules!K6 -> 4440.4358 | L12: =L7-Schedules!L6 -> 6344.8062 | M12: =M7-Schedules!M6 -> 7839.9126
A14: Unlevered Free Cash Flow to Firm (FCFF) — DCF Input
A15: EBIT | I15: ='Income Statement'!I10 -> 5552.8673 | J15: ='Income Statement'!J10 -> 7164.99 | K15: ='Income Statement'!K10 -> 8974.15 | L15: ='Income Statement'!L10 -> 10814.657 | M15: ='Income Statement'!M10 -> 12596.912
A16: NOPAT = EBIT × (1 − tax rate) | I16: =I15*(1-Assumptions!$B$12) -> 4164.6504 | J16: =J15*(1-Assumptions!$B$12) -> 5373.7425 | K16: =K15*(1-Assumptions!$B$12) -> 6730.6125 | L16: =L15*(1-Assumptions!$B$12) -> 8110.9926 | M16: =M15*(1-Assumptions!$B$12) -> 9447.6842
A17: Add: D&A | I17: ='Income Statement'!I9 -> 1612.1227 | J17: ='Income Statement'!J9 -> 2015.1534 | K17: ='Income Statement'!K9 -> 2310.7093 | L17: ='Income Statement'!L9 -> 2471.9216 | M17: ='Income Statement'!M9 -> 2630.1245
A18: Less: Capex | I18: =Schedules!I6 -> 2865.996 | J18: =Schedules!J6 -> 3134.6831 | K18: =Schedules!K6 -> 3224.2455 | L18: =Schedules!L6 -> 3089.9019 | M18: =Schedules!M6 -> 3114.6212
A19: Less: Δ Net Working Capital | I19: =I5 -> 1393.1925 | J19: =J5 -> 1253.8733 | K19: =K5 -> 1074.7485 | L19: =L5 -> 806.06137 | M19: =M5 -> 741.57647
A20: FCFF | I20: =I16+I17-I18-I19 -> 1517.5847 | J20: =J16+J17-J18-J19 -> 3000.3396 | K20: =K16+K17-K18-K19 -> 4742.3278 | L20: =L16+L17-L18-L19 -> 6686.9508 | M20: =M16+M17-M18-M19 -> 8221.6111

Sheet Ratios
A1: RATIO ANALYSIS — Recomputed From The Model (All 12 Years)
A3: ₹ Crore, Consolidated | B3: FY20 | C3: FY21 | D3: FY22 | E3: FY23 | F3: FY24 | G3: FY25 | H3: FY26 | I3: FY27E | J3: FY28E | K3: FY29E | L3: FY30E | M3: FY31E
A5: Revenue Growth % YoY | C5: ='Income Statement'!C6 -> -0.021543086 | D5: ='Income Statement'!D6 -> 0.46134153 | E5: ='Income Statement'!E6 -> 1.365452 | F5: ='Income Statement'!F6 -> 0.68834247 | G5: ='Income Statement'!G6 -> 0.26723987 | H5: ='Income Statement'!H6 -> 0.83723345 | I5: ='Income Statement'!I6 -> 0.35 | J5: ='Income Statement'!J6 -> 0.25 | ... M5: ='Income Statement'!M6 -> 0.12
A6: EBITDA Margin % | B6: ='Income Statement'!B8 -> 0.046593186 | C6: ='Income Statement'!C8 -> 0.043522785 | D6: ='Income Statement'!D8 -> 0.037140855 | E6: ='Income Statement'!E8 -> 0.12383351 | F6: ='Income Statement'!F8 -> 0.1380944 | G6: ='Income Statement'!G8 -> 0.18845195 | H6: ='Income Statement'!H8 -> 0.22267023 | I6: ='Income Statement'!I8 -> 0.2 | ... M6: ='Income Statement'!M8 -> 0.22
A7: Net Profit Margin % | B7: ='Income Statement'!B17 -> 0.019704409 | C7: ='Income Statement'!C17 -> 0.024731183 | D7: ='Income Statement'!D17 -> 0.02793623 | E7: ='Income Statement'!E17 -> 0.074317879 | F7: ='Income Statement'!F17 -> 0.11099228 | G7: ='Income Statement'!G17 -> 0.13323872 | H7: ='Income Statement'!H17 -> 0.14658929 | I7: ='Income Statement'!I17 -> 0.11002251 | ... M7: ='Income Statement'!M17 -> 0.13098523
A8: Return on Equity % (avg equity) | C8: ='Income Statement'!C16/AVERAGE('Balance Sheet'!B7:C7) -> 0.15023328 | D8: ='Income Statement'!D16/AVERAGE('Balance Sheet'!C7:D7) -> 0.20628719 | E8: ='Income Statement'!E16/AVERAGE('Balance Sheet'!D7:E7) -> 0.44282436 | F8: ='Income Statement'!F16/AVERAGE('Balance Sheet'!E7:F7) -> 0.42696254 | G8: ='Income Statement'!G16/AVERAGE('Balance Sheet'!F7:G7) -> 0.2837031 | H8: ='Income Statement'!H16/AVERAGE('Balance Sheet'!G7:H7) -> 0.32529498 | I8: ='Income Statement'!I16/AVERAGE('Balance Sheet'!H7:I7) -> 0.24078834 | J8: ='Income Statement'!J16/AVERAGE('Balance Sheet'!I7:J7) -> 0.24571951 | ... M8: ='Income Statement'!M16/AVERAGE('Balance Sheet'!L7:M7) -> 0.2175829
A9: Return on Capital Employed % (avg CE=Equity+Debt) | C9: ='Income Statement'!C10/((('Balance Sheet'!B7+'Balance Sheet'!B8)+('Balance Sheet'!C7+'Balance Sheet'!C8))/2) -> 0.098245614 | D9: ='Income Statement'!D10/((('Balance Sheet'!C7+'Balance Sheet'!C8)+('Balance Sheet'!D7+'Balance Sheet'!D8))/2) -> 0.085365854 | E9: ='Income Statement'!E10/((('Balance Sheet'!D7+'Balance Sheet'!D8)+('Balance Sheet'!E7+'Balance Sheet'!E8))/2) -> 0.45574771 | F9: ='Income Statement'!F10/((('Balance Sheet'!E7+'Balance Sheet'!E8)+('Balance Sheet'!F7+'Balance Sheet'!F8))/2) -> 0.3815267 | G9: ='Income Statement'!G10/((('Balance Sheet'!F7+'Balance Sheet'!F8)+('Balance Sheet'!G7+'Balance Sheet'!G8))/2) -> 0.30289183 | H9: ='Income Statement'!H10/((('Balance Sheet'!G7+'Balance Sheet'!G8)+('Balance Sheet'!H7+'Balance Sheet'!H8))/2) -> 0.34727664 | I9: ='Income Statement'!I10/((('Balance Sheet'!H7+'Balance Sheet'!H8)+('Balance Sheet'!I7+'Balance Sheet'!I8))/2) -> 0.27947449 | J9: ='Income Statement'!J10/((('Balance Sheet'!I7+'Balance Sheet'!I8)+('Balance Sheet'!J7+'Balance Sheet'!J8))/2) -> 0.28768754 | ... M9: ='Income Statement'!M10/((('Balance Sheet'!L7+'Balance Sheet'!L8)+('Balance Sheet'!M7+'Balance Sheet'!M8))/2) -> 0.26433981
A10: Debt / Equity (x) | B10: ='Balance Sheet'!B8/'Balance Sheet'!B7 -> 0.52684564 | C10: ='Balance Sheet'!C8/'Balance Sheet'!C7 -> 0.98550725 | D10: ='Balance Sheet'!D8/'Balance Sheet'!D7 -> 0.84813084 | E10: ='Balance Sheet'!E8/'Balance Sheet'!E7 -> 0.17410229 | F10: ='Balance Sheet'!F8/'Balance Sheet'!F7 -> 0.13527397 | G10: ='Balance Sheet'!G8/'Balance Sheet'!G7 -> 0.12649014 | H10: ='Balance Sheet'!H8/'Balance Sheet'!H7 -> 0.22253775 | I10: ='Balance Sheet'!I8/'Balance Sheet'!I7 -> 0.20688799 | ... M10: ='Balance Sheet'!M8/'Balance Sheet'!M7 -> 0.13660825
A11: Interest Coverage (EBIT/Interest, x) | B11: ='Income Statement'!B10/'Income Statement'!B12 -> 1.9411765 | C11: ='Income Statement'!C10/'Income Statement'!C12 -> 1.8064516 | D11: ='Income Statement'!D10/'Income Statement'!D12 -> 1.5365854 | E11: ='Income Statement'!E10/'Income Statement'!E12 -> 8.195122 | F11: ='Income Statement'!F10/'Income Statement'!F12 -> 9.2642857 | G11: ='Income Statement'!G10/'Income Statement'!G12 -> 15.263158 | H11: ='Income Statement'!H10/'Income Statement'!H12 -> 17.567857 | I11: ='Income Statement'!I10/'Income Statement'!I12 -> 18.667236 | ... M11: ='Income Statement'!M10/'Income Statement'!M12 -> 24.751693
A12: Asset Turnover (Revenue/Total Assets, x) | B12: ='Income Statement'!B5/'Balance Sheet'!B18 -> 2.1279318 | C12: ='Income Statement'!C5/'Balance Sheet'!C18 -> 1.5245902 | D12: ='Income Statement'!D5/'Balance Sheet'!D18 -> 1.3249768 | E12: ='Income Statement'!E5/'Balance Sheet'!E18 -> 0.9116813 | F12: ='Income Statement'!F5/'Balance Sheet'!F18 -> 1.0108194 | G12: ='Income Statement'!G5/'Balance Sheet'!G18 -> 0.73297473 | H12: ='Income Statement'!H5/'Balance Sheet'!H18 -> 0.88115952 | I12: ='Income Statement'!I5/'Balance Sheet'!I18 -> 0.92060271 | ... M12: ='Income Statement'!M5/'Balance Sheet'!M18 -> 0.81505438
A13: EPS (₹) | B13: ='Income Statement'!B18 -> 2.12 | C13: ='Income Statement'!C18 -> 2.5 | D13: ='Income Statement'!D18 -> 3.84 | E13: ='Income Statement'!E18 -> 24.49 | F13: ='Income Statement'!F18 -> 62.76 | G13: ='Income Statement'!G18 -> 65 | H13: ='Income Statement'!H18 -> 129.02 | I13: ='Income Statement'!I18 -> 130.94854 | ... M13: ='Income Statement'!M18 -> 301.19554
A15: All ratios above are LIVE formulas referencing the Income Statement and Balance Sheet tabs — they will recalculate automatically if any Assumptions cell is changed, unlike the static ratio table in Part I (which was computed once from historical actuals only).

Sheet DCF Valuation
A1: DCF VALUATION — Live, Driven by Assumptions Tab
A3: ₹ Crore | I3: FY27E | J3: FY28E | K3: FY29E | L3: FY30E | M3: FY31E
A4: FCFF | I4: ='Cash Flow'!I20 -> 1517.5847 | J4: ='Cash Flow'!J20 -> 3000.3396 | K4: ='Cash Flow'!K20 -> 4742.3278 | L4: ='Cash Flow'!L20 -> 6686.9508 | M4: ='Cash Flow'!M20 -> 8221.6111
A5: Discount Period (n) | I5: =COLUMN(I5)-COLUMN($H$5) -> 1 | J5: =COLUMN(J5)-COLUMN($H$5) -> 2 | K5: =COLUMN(K5)-COLUMN($H$5) -> 3 | L5: =COLUMN(L5)-COLUMN($H$5) -> 4 | M5: =COLUMN(M5)-COLUMN($H$5) -> 5
A6: Discount Factor @ WACC | I6: =1/(1+Assumptions!$B$28)^I5 -> 0.87901295 | J6: =1/(1+Assumptions!$B$28)^J5 -> 0.77266376 | K6: =1/(1+Assumptions!$B$28)^K5 -> 0.67918145 | L6: =1/(1+Assumptions!$B$28)^L5 -> 0.59700929 | M6: =1/(1+Assumptions!$B$28)^M5 -> 0.5247789
A7: PV of FCFF | I7: =I4*I6 -> 1333.9766 | J7: =J4*J6 -> 2318.2537 | K7: =K4*K6 -> 3220.9011 | L7: =L4*L6 -> 3992.1718 | M7: =M4*M6 -> 4314.528
A9: Sum of PV of Explicit FCFF (FY27E-FY31E) | B9: =SUM(I7:M7) -> 15179.831
A11: Terminal Value (Gordon Growth) | B11: =M4*(1+Assumptions!$B$29)/(Assumptions!$B$28-Assumptions!$B$29) -> 98502.103
A12: PV of Terminal Value | B12: =B11*M6 -> 51691.825
A13: Terminal Value as % of Enterprise Value | B13: =B12/(B9+B12) -> 0.77300052
A15: Enterprise Value | B15: =B9+B12 -> 66871.656
A16: Less: Net Debt | B16: =Assumptions!B33 -> 2260
A17: Equity Value | B17: =B15-B16 -> 64611.656
A18: Diluted Shares Outstanding (Cr) | B18: =Assumptions!B34 -> 30.1
A19: Intrinsic Value per Share (₹) | B19: =B17/B18 -> 2146.5666
A21: CMP (₹) | B21: =Assumptions!B35 -> 2886
A22: Upside / (Downside) to CMP | B22: =B19/B21-1 -> -0.25621391
A24: This entire sheet recalculates live off the Assumptions tab (WACC build, terminal growth, net debt, shares outstanding) and the Cash Flow tab's FCFF (which itself flows from Income Statement/Schedules forecasts). Change any Assumptions cell to re-run the valuation instantly — this is the primary advantage of a model over the static Part II Word document.

Sheet Sensitivity
A1: SENSITIVITY — Intrinsic Value per Share (₹) — Live Grid, WACC × Terminal Growth
A3: WACC (rows) vs. Terminal Growth g (columns)
A4: WACC ↓ | B4: g → | C4: 0.03 | D4: 0.04 | E4: 0.05 | F4: 0.06 | G4: 0.07
B5: 0.118 | C5: =IFERROR((SUMPRODUCT('Cash Flow'!$I$20:$M$20,1/(1+$B5)^(COLUMN('Cash Flow'!$I$20:$M$20)-COLUMN('Cash Flow'!$I$20)+1))+('Cash Flow'!$M$20*(1+C$4))/($B5-C$4)/(1+$B5)^5-Assumptions!$B$33)/Assumptions!$B$34,"n/a") -> 2291.4434 | D5: =IFERROR((SUMPRODUCT('Cash Flow'!$I$20:$M$20,1/(1+$B5)^(COLUMN('Cash Flow'!$I$20:$M$20)-COLUMN('Cash Flow'!$I$20)+1))+('Cash Flow'!$M$20*(1+D$4))/($B5-D$4)/(1+$B5)^5-Assumptions!$B$33)/Assumptions!$B$34,"n/a") -> 2546.1534 | E5: =IFERROR((SUMPRODUCT('Cash Flow'!$I$20:$M$20,1/(1+$B5)^(COLUMN('Cash Flow'!$I$20:$M$20)-COLUMN('Cash Flow'!$I$20)+1))+('Cash Flow'!$M$20*(1+E$4))/($B5-E$4)/(1+$B5)^5-Assumptions!$B$33)/Assumptions!$B$34,"n/a") -> 2875.778 | F5: =IFERROR((SUMPRODUCT('Cash Flow'!$I$20:$M$20,1/(1+$B5)^(COLUMN('Cash Flow'!$I$20:$M$20)-COLUMN('Cash Flow'!$I$20)+1))+('Cash Flow'!$M$20*(1+F$4))/($B5-F$4)/(1+$B5)^5-Assumptions!$B$33)/Assumptions!$B$34,"n/a") -> 3319.0664 | G5: =IFERROR((SUMPRODUCT('Cash Flow'!$I$20:$M$20,1/(1+$B5)^(COLUMN('Cash Flow'!$I$20:$M$20)-COLUMN('Cash Flow'!$I$20)+1))+('Cash Flow'!$M$20*(1+G$4))/($B5-G$4)/(1+$B5)^5-Assumptions!$B$33)/Assumptions!$B$34,"n/a") -> 3947.0582
B6: 0.128 | C6: =IFERROR((SUMPRODUCT('Cash Flow'!$I$20:$M$20,1/(1+$B6)^(COLUMN('Cash Flow'!$I$20:$M$20)-COLUMN('Cash Flow'!$I$20)+1))+('Cash Flow'!$M$20*(1+C$4))/($B6-C$4)/(1+$B6)^5-Assumptions!$B$33)/Assumptions!$B$34,"n/a") -> 2016.5332 | D6: =IFERROR((SUMPRODUCT('Cash Flow'!$I$20:$M$20,1/(1+$B6)^(COLUMN('Cash Flow'!$I$20:$M$20)-COLUMN('Cash Flow'!$I$20)+1))+('Cash Flow'!$M$20*(1+D$4))/($B6-D$4)/(1+$B6)^5-Assumptions!$B$33)/Assumptions!$B$34,"n/a") -> 2212.1677 | E6: =IFERROR((SUMPRODUCT('Cash Flow'!$I$20:$M$20,1/(1+$B6)^(COLUMN('Cash Flow'!$I$20:$M$20)-COLUMN('Cash Flow'!$I$20)+1))+('Cash Flow'!$M$20*(1+E$4))/($B6-E$4)/(1+$B6)^5-Assumptions!$B$33)/Assumptions!$B$34,"n/a") -> 2457.9648 | F6: =IFERROR((SUMPRODUCT('Cash Flow'!$I$20:$M$20,1/(1+$B6)^(COLUMN('Cash Flow'!$I$20:$M$20)-COLUMN('Cash Flow'!$I$20)+1))+('Cash Flow'!$M$20*(1+F$4))/($B6-F$4)/(1+$B6)^5-Assumptions!$B$33)/Assumptions!$B$34,"n/a") -> 2776.0551 | G6: =IFERROR((SUMPRODUCT('Cash Flow'!$I$20:$M$20,1/(1+$B6)^(COLUMN('Cash Flow'!$I$20:$M$20)-COLUMN('Cash Flow'!$I$20)+1))+('Cash Flow'!$M$20*(1+G$4))/($B6-G$4)/(1+$B6)^5-Assumptions!$B$33)/Assumptions!$B$34,"n/a") -> 3203.8318
B7: 0.138 | C7: =IFERROR((SUMPRODUCT('Cash Flow'!$I$20:$M$20,1/(1+$B7)^(COLUMN('Cash Flow'!$I$20:$M$20)-COLUMN('Cash Flow'!$I$20)+1))+('Cash Flow'!$M$20*(1+C$4))/($B7-C$4)/(1+$B7)^5-Assumptions!$B$33)/Assumptions!$B$34,"n/a") -> 1793.5453 | D7: =IFERROR((SUMPRODUCT('Cash Flow'!$I$20:$M$20,1/(1+$B7)^(COLUMN('Cash Flow'!$I$20:$M$20)-COLUMN('Cash Flow'!$I$20)+1))+('Cash Flow'!$M$20*(1+D$4))/($B7-D$4)/(1+$B7)^5-Assumptions!$B$33)/Assumptions!$B$34,"n/a") -> 1947.4215 | E7: =IFERROR((SUMPRODUCT('Cash Flow'!$I$20:$M$20,1/(1+$B7)^(COLUMN('Cash Flow'!$I$20:$M$20)-COLUMN('Cash Flow'!$I$20)+1))+('Cash Flow'!$M$20*(1+E$4))/($B7-E$4)/(1+$B7)^5-Assumptions!$B$33)/Assumptions!$B$34,"n/a") -> 2136.2696 | F7: =IFERROR((SUMPRODUCT('Cash Flow'!$I$20:$M$20,1/(1+$B7)^(COLUMN('Cash Flow'!$I$20:$M$20)-COLUMN('Cash Flow'!$I$20)+1))+('Cash Flow'!$M$20*(1+F$4))/($B7-F$4)/(1+$B7)^5-Assumptions!$B$33)/Assumptions!$B$34,"n/a") -> 2373.5403 | G7: =IFERROR((SUMPRODUCT('Cash Flow'!$I$20:$M$20,1/(1+$B7)^(COLUMN('Cash Flow'!$I$20:$M$20)-COLUMN('Cash Flow'!$I$20)+1))+('Cash Flow'!$M$20*(1+G$4))/($B7-G$4)/(1+$B7)^5-Assumptions!$B$33)/Assumptions!$B$34,"n/a") -> 2680.5965
B8: 0.148 | C8: =IFERROR((SUMPRODUCT('Cash Flow'!$I$20:$M$20,1/(1+$B8)^(COLUMN('Cash Flow'!$I$20:$M$20)-COLUMN('Cash Flow'!$I$20)+1))+('Cash Flow'!$M$20*(1+C$4))/($B8-C$4)/(1+$B8)^5-Assumptions!$B$33)/Assumptions!$B$34,"n/a") -> 1609.2383 | D8: =IFERROR((SUMPRODUCT('Cash Flow'!$I$20:$M$20,1/(1+$B8)^(COLUMN('Cash Flow'!$I$20:$M$20)-COLUMN('Cash Flow'!$I$20)+1))+('Cash Flow'!$M$20*(1+D$4))/($B8-D$4)/(1+$B8)^5-Assumptions!$B$33)/Assumptions!$B$34,"n/a") -> 1732.6388 | E8: =IFERROR((SUMPRODUCT('Cash Flow'!$I$20:$M$20,1/(1+$B8)^(COLUMN('Cash Flow'!$I$20:$M$20)-COLUMN('Cash Flow'!$I$20)+1))+('Cash Flow'!$M$20*(1+E$4))/($B8-E$4)/(1+$B8)^5-Assumptions!$B$33)/Assumptions!$B$34,"n/a") -> 1881.2232 | F8: =IFERROR((SUMPRODUCT('Cash Flow'!$I$20:$M$20,1/(1+$B8)^(COLUMN('Cash Flow'!$I$20:$M$20)-COLUMN('Cash Flow'!$I$20)+1))+('Cash Flow'!$M$20*(1+F$4))/($B8-F$4)/(1+$B8)^5-Assumptions!$B$33)/Assumptions!$B$34,"n/a") -> 2063.5767 | G8: =IFERROR((SUMPRODUCT('Cash Flow'!$I$20:$M$20,1/(1+$B8)^(COLUMN('Cash Flow'!$I$20:$M$20)-COLUMN('Cash Flow'!$I$20)+1))+('Cash Flow'!$M$20*(1+G$4))/($B8-G$4)/(1+$B8)^5-Assumptions!$B$33)/Assumptions!$B$34,"n/a") -> 2292.6875
B9: 0.158 | C9: =IFERROR((SUMPRODUCT('Cash Flow'!$I$20:$M$20,1/(1+$B9)^(COLUMN('Cash Flow'!$I$20:$M$20)-COLUMN('Cash Flow'!$I$20)+1))+('Cash Flow'!$M$20*(1+C$4))/($B9-C$4)/(1+$B9)^5-Assumptions!$B$33)/Assumptions!$B$34,"n/a") -> 1454.5109 | D9: =IFERROR((SUMPRODUCT('Cash Flow'!$I$20:$M$20,1/(1+$B9)^(COLUMN('Cash Flow'!$I$20:$M$20)-COLUMN('Cash Flow'!$I$20)+1))+('Cash Flow'!$M$20*(1+D$4))/($B9-D$4)/(1+$B9)^5-Assumptions!$B$33)/Assumptions!$B$34,"n/a") -> 1555.0799 | E9: =IFERROR((SUMPRODUCT('Cash Flow'!$I$20:$M$20,1/(1+$B9)^(COLUMN('Cash Flow'!$I$20:$M$20)-COLUMN('Cash Flow'!$I$20)+1))+('Cash Flow'!$M$20*(1+E$4))/($B9-E$4)/(1+$B9)^5-Assumptions!$B$33)/Assumptions!$B$34,"n/a") -> 1674.2728 | F9: =IFERROR((SUMPRODUCT('Cash Flow'!$I$20:$M$20,1/(1+$B9)^(COLUMN('Cash Flow'!$I$20:$M$20)-COLUMN('Cash Flow'!$I$20)+1))+('Cash Flow'!$M$20*(1+F$4))/($B9-F$4)/(1+$B9)^5-Assumptions!$B$33)/Assumptions!$B$34,"n/a") -> 1817.7908 | G9: =IFERROR((SUMPRODUCT('Cash Flow'!$I$20:$M$20,1/(1+$B9)^(COLUMN('Cash Flow'!$I$20:$M$20)-COLUMN('Cash Flow'!$I$20)+1))+('Cash Flow'!$M$20*(1+G$4))/($B9-G$4)/(1+$B9)^5-Assumptions!$B$33)/Assumptions!$B$34,"n/a") -> 1993.9265
A11: Every cell is a live formula (not a pasted value): it recomputes PV of FY27E-FY31E FCFF at that row's WACC, adds a Gordon Growth terminal value at that column's g, subtracts net debt, and divides by shares — all pulled directly from the Cash Flow and Assumptions tabs. Compare to the base case on the DCF Valuation tab (WACC≈13.8%, g=5.0%) which should reconcile closely to the row-13.8%/g-5.0% cell here (interpolated).

Sheet Checks
A1: CHECKS — Model Integrity
A3: Check | B3: FY20 | C3: FY21 | D3: FY22 | E3: FY23 | F3: FY24 | G3: FY25 | H3: FY26 | I3: FY27E | J3: FY28E | K3: FY29E | L3: FY30E | M3: FY31E
A4: Balance Sheet balances? (Assets − Liabilities = 0, ±1 Cr tolerance for source rounding) | B4: =IF(ABS('Balance Sheet'!B20)<=1,"OK","CHECK") -> OK | C4: =IF(ABS('Balance Sheet'!C20)<=1,"OK","CHECK") -> OK | D4: =IF(ABS('Balance Sheet'!D20)<=1,"OK","CHECK") -> OK | E4: =IF(ABS('Balance Sheet'!E20)<=1,"OK","CHECK") -> OK | F4: =IF(ABS('Balance Sheet'!F20)<=1,"OK","CHECK") -> OK | G4: =IF(ABS('Balance Sheet'!G20)<=1,"OK","CHECK") -> OK | H4: =IF(ABS('Balance Sheet'!H20)<=1,"OK","CHECK") -> OK | I4: =IF(ABS('Balance Sheet'!I20)<=1,"OK","CHECK") -> OK | ... M4: =IF(ABS('Balance Sheet'!M20)<=1,"OK","CHECK") -> OK
A6: EBITDA margin within 0-100%? | B6: =IF(AND('Income Statement'!B8>=0,'Income Statement'!B8<=1),"OK","CHECK") -> OK | C6: =IF(AND('Income Statement'!C8>=0,'Income Statement'!C8<=1),"OK","CHECK") -> OK | D6: =IF(AND('Income Statement'!D8>=0,'Income Statement'!D8<=1),"OK","CHECK") -> OK | E6: =IF(AND('Income Statement'!E8>=0,'Income Statement'!E8<=1),"OK","CHECK") -> OK | F6: =IF(AND('Income Statement'!F8>=0,'Income Statement'!F8<=1),"OK","CHECK") -> OK | G6: =IF(AND('Income Statement'!G8>=0,'Income Statement'!G8<=1),"OK","CHECK") -> OK | H6: =IF(AND('Income Statement'!H8>=0,'Income Statement'!H8<=1),"OK","CHECK") -> OK | I6: =IF(AND('Income Statement'!I8>=0,'Income Statement'!I8<=1),"OK","CHECK") -> OK | ... M6: =IF(AND('Income Statement'!M8>=0,'Income Statement'!M8<=1),"OK","CHECK") -> OK
A8: WACC > Terminal growth g? (required for TV formula) | B8: =IF(Assumptions!B28>Assumptions!B29,"OK","CHECK — TV FORMULA INVALID") -> OK
A10: Net Profit ties: PBT - Tax = Net Profit? | B10: =IF(ABS(('Income Statement'!B13-'Income Statement'!B15)-'Income Statement'!B16)<1,"OK","CHECK") -> OK | C10: =IF(ABS(('Income Statement'!C13-'Income Statement'!C15)-'Income Statement'!C16)<1,"OK","CHECK") -> OK | D10: =IF(ABS(('Income Statement'!D13-'Income Statement'!D15)-'Income Statement'!D16)<1,"OK","CHECK") -> OK | E10: =IF(ABS(('Income Statement'!E13-'Income Statement'!E15)-'Income Statement'!E16)<1,"OK","CHECK") -> OK | F10: =IF(ABS(('Income Statement'!F13-'Income Statement'!F15)-'Income Statement'!F16)<1,"OK","CHECK") -> OK | G10: =IF(ABS(('Income Statement'!G13-'Income Statement'!G15)-'Income Statement'!G16)<1,"OK","CHECK") -> OK | H10: =IF(ABS(('Income Statement'!H13-'Income Statement'!H15)-'Income Statement'!H16)<1,"OK","CHECK") -> OK | I10: =IF(ABS(('Income Statement'!I13-'Income Statement'!I15)-'Income Statement'!I16)<1,"OK","CHECK") -> OK | ... M10: =IF(ABS(('Income Statement'!M13-'Income Statement'!M15)-'Income Statement'!M16)<1,"OK","CHECK") -> OK
A12: All rows should read 'OK' across every year before this model is used for decision-making. If any cell reads 'CHECK', trace the referenced formula on the named tab before trusting downstream valuation output.
